clipper/__init__.py
clipper/__main__.py
clipper/cli.py
clipper/core.py
clipper_ai-0.1.0.dist-info/licenses/LICENSE
clipper_ai-0.1.0.dist-info/METADATA
clipper_ai-0.1.0.dist-info/WHEEL
clipper_ai-0.1.0.dist-info/entry_points.txt
clipper_ai-0.1.0.dist-info/top_level.txt
clipper_ai-0.1.0.dist-info/RECORD
