Metadata-Version: 2.4
Name: clipper-ai
Version: 0.1.0
Summary: Batch image generation for webui_forge using prompts
Author: Ernan Hughes
Author-email: ernanhughes@gmail.com
Classifier: Programming Language :: Python :: 3
Classifier: License :: OSI Approved :: MIT License
License-File: LICENSE
Requires-Dist: requests
Dynamic: author
Dynamic: author-email
Dynamic: classifier
Dynamic: license-file
Dynamic: requires-dist
Dynamic: summary
